explabox/__init__.py
explabox/_version.py
explabox/config.py
explabox/explabox.py
explabox/mixins.py
explabox/digestibles/__init__.py
explabox/digestibles/digestibles.py
explabox/examine/__init__.py
explabox/examine/examiner.py
explabox/explain/__init__.py
explabox/explain/text/__init__.py
explabox/explain/text/explainer.py
explabox/explore/__init__.py
explabox/explore/explorer.py
explabox/expose/__init__.py
explabox/expose/text/__init__.py
explabox/expose/text/characters.py
explabox/expose/text/exposer.py
explabox/expose/text/sentences.py
explabox/expose/text/words.py
explabox/ingestibles/__init__.py
explabox/ingestibles/data.py
explabox/ingestibles/ingestible.py
explabox/ingestibles/model.py
explabox/ui/__init__.py
explabox/ui/notebook.py
explabox/utils/__init__.py
explabox/utils/io.py
explabox-1.0.3.dist-info/licenses/LICENSE
explabox-1.0.3.dist-info/METADATA
explabox-1.0.3.dist-info/WHEEL
explabox-1.0.3.dist-info/top_level.txt
explabox-1.0.3.dist-info/RECORD
