Metadata-Version: 2.4
Name: explabox
Version: 1.0.3
Summary: Explore/examine/explain/expose your model with the explabox!
Home-page: https://explabox.rtfd.io
Author: Marcel Robeer for NPAI and other contributors
License: GNU LGPL v3
Classifier: Development Status :: 5 - Production/Stable
Classifier: Intended Audience :: Developers
Classifier: Intended Audience :: Education
Classifier: Intended Audience :: Science/Research
Classifier: Programming Language :: Python
Classifier: Programming Language :: Python :: 3
Classifier: Programming Language :: Python :: 3.8
Classifier: Programming Language :: Python :: 3.9
Classifier: Programming Language :: Python :: 3.10
Classifier: Programming Language :: Python :: 3.11
Classifier: Programming Language :: Python :: 3.12
Classifier: Operating System :: OS Independent
Classifier: License :: OSI Approved :: GNU Lesser General Public License v3 or later (LGPLv3+)
Classifier: Topic :: Scientific/Engineering :: Artificial Intelligence
Requires-Python: >=3.8
License-File: LICENSE
Requires-Dist: genbase>=0.3.6
Requires-Dist: instancelib>=0.5.0
Requires-Dist: instancelib-onnx>=0.1.3
Requires-Dist: text_explainability>=0.7.2
Requires-Dist: text_sensitivity>=0.3.5
Requires-Dist: numpy<2,>=1.23.0
Provides-Extra: docs
Requires-Dist: m2r>=0.2.1; extra == "docs"
Requires-Dist: sphinx>=4.1.1; extra == "docs"
Requires-Dist: sphinx-autodoc-typehints>=1.17.0; extra == "docs"
Requires-Dist: sphinxcontrib-apidoc>=0.3.0; extra == "docs"
Requires-Dist: doc8; extra == "docs"
Provides-Extra: quality
Requires-Dist: isort; extra == "quality"
Requires-Dist: black; extra == "quality"
Requires-Dist: check-manifest; extra == "quality"
Requires-Dist: doc8; extra == "quality"
Requires-Dist: flake8>=4.0.0; extra == "quality"
Provides-Extra: test
Requires-Dist: pytest-helpers-namespace>=2021.12.29; extra == "test"
Requires-Dist: genbase-test-helpers>=0.1.1; extra == "test"
Requires-Dist: pytest>=6.2.4; extra == "test"
Requires-Dist: coverage>=6.1.2; extra == "test"
Provides-Extra: dev
Requires-Dist: m2r>=0.2.1; extra == "dev"
Requires-Dist: isort; extra == "dev"
Requires-Dist: flake8>=4.0.0; extra == "dev"
Requires-Dist: sphinx>=4.1.1; extra == "dev"
Requires-Dist: check-manifest; extra == "dev"
Requires-Dist: pytest-helpers-namespace>=2021.12.29; extra == "dev"
Requires-Dist: pytest>=6.2.4; extra == "dev"
Requires-Dist: sphinxcontrib-apidoc>=0.3.0; extra == "dev"
Requires-Dist: doc8; extra == "dev"
Requires-Dist: genbase-test-helpers>=0.1.1; extra == "dev"
Requires-Dist: black; extra == "dev"
Requires-Dist: coverage>=6.1.2; extra == "dev"
Requires-Dist: sphinx-autodoc-typehints>=1.17.0; extra == "dev"
Requires-Dist: make-to-batch>=0.2.3; extra == "dev"
Provides-Extra: all
Requires-Dist: m2r>=0.2.1; extra == "all"
Requires-Dist: isort; extra == "all"
Requires-Dist: flake8>=4.0.0; extra == "all"
Requires-Dist: make-to-batch>=0.2.3; extra == "all"
Requires-Dist: sphinx>=4.1.1; extra == "all"
Requires-Dist: check-manifest; extra == "all"
Requires-Dist: pytest-helpers-namespace>=2021.12.29; extra == "all"
Requires-Dist: pytest>=6.2.4; extra == "all"
Requires-Dist: sphinxcontrib-apidoc>=0.3.0; extra == "all"
Requires-Dist: doc8; extra == "all"
Requires-Dist: genbase-test-helpers>=0.1.1; extra == "all"
Requires-Dist: black; extra == "all"
Requires-Dist: coverage>=6.1.2; extra == "all"
Requires-Dist: sphinx-autodoc-typehints>=1.17.0; extra == "all"
Dynamic: author
Dynamic: classifier
Dynamic: description
Dynamic: description-content-type
Dynamic: home-page
Dynamic: license
Dynamic: license-file
Dynamic: provides-extra
Dynamic: requires-dist
Dynamic: requires-python
Dynamic: summary
